cognitojwt/__init__.py
cognitojwt/constants.py
cognitojwt/exceptions.py
cognitojwt/jwt_sync.py
cognitojwt/token_utils.py
clp_cognitojwt-1.3.1.dist-info/LICENSE
clp_cognitojwt-1.3.1.dist-info/METADATA
clp_cognitojwt-1.3.1.dist-info/WHEEL
clp_cognitojwt-1.3.1.dist-info/top_level.txt
clp_cognitojwt-1.3.1.dist-info/RECORD
