Metadata-Version: 2.1
Name: clp-cognitojwt
Version: 1.3.1
Summary: Decode and verify Amazon Cognito JWT tokens
Home-page: http://github.com/chrispruitt/cognitojwt
Author: Chris Pruitt
Author-email: chris.pruitt15@gmail.com
License: MIT
Keywords: Amazon Cognito JWT
Platform: Any
Classifier: Development Status :: 4 - Beta
Classifier: Intended Audience :: Developers
Classifier: License :: OSI Approved :: MIT License
Classifier: Programming Language :: Python :: 3.6
Classifier: Programming Language :: Python :: 3.7
Classifier: Operating System :: OS Independent
Requires-Dist: python-jose
Requires-Dist: requests
Provides-Extra: test
Requires-Dist: aiohttp ; extra == 'test'
Requires-Dist: requests ; extra == 'test'
Requires-Dist: attrs (==19.1.0) ; extra == 'test'
Requires-Dist: pytest (==5.4.0) ; extra == 'test'
Requires-Dist: async-lru ; extra == 'test'
